codezen/__init__.py
codezen/__main__.py
codezen/app.py
codezen/ignore_files.py
codezen-0.4.0.dist-info/LICENSE
codezen-0.4.0.dist-info/METADATA
codezen-0.4.0.dist-info/WHEEL
codezen-0.4.0.dist-info/entry_points.txt
codezen-0.4.0.dist-info/RECORD
