Metadata-Version: 2.1
Name: codezen
Version: 0.4.0
Summary: Your indispensable partner in programming
Home-page: https://github.com/mmaorc/codezen
Author: Maor Cohen
Author-email: me@maorcohen.net
Requires-Python: >=3.11,<4.0
Classifier: Programming Language :: Python :: 3
Classifier: Programming Language :: Python :: 3.11
Requires-Dist: binaryornot (>=0.4.4,<0.5.0)
Requires-Dist: langchain (>=0.0.177,<0.0.178)
Requires-Dist: openai (>=0.27.7,<0.28.0)
Requires-Dist: pathspec (>=0.11.1,<0.12.0)
Requires-Dist: tiktoken (>=0.4.0,<0.5.0)
Requires-Dist: typer (>=0.9.0,<0.10.0)
